sherlock/__init__.py
sherlock/__main__.py
sherlock/complexity.py
sherlock/config.py
sherlock/core.py
sherlock/exceptions.py
sherlock/file_utils.py
sherlock/model.py
sherlock/version.py
sherlock/visitor.py
sherlock/report/__init__.py
sherlock/report/html.py
sherlock/report/html.template
sherlock/report/json.py
sherlock/report/print.py
tests/__init__.py
tests/atest/__init__.py
tests/atest/test_example_workflow.py
tests/atest/aliased_library/__init__.py
tests/atest/aliased_library/test_aliased_library.py
tests/atest/complicated_structure/__init__.py
tests/atest/complicated_structure/test_complicated_structure.py
tests/atest/dict_variables/__init__.py
tests/atest/dict_variables/test_dict_variables.py
tests/atest/duplicated_imports/__init__.py
tests/atest/duplicated_imports/test_duplicated_imports.py
tests/atest/duplicated_names_dotted/__init__.py
tests/atest/duplicated_names_dotted/test_duplicated_names_dotted.py
tests/atest/empty_keywords/__init__.py
tests/atest/empty_keywords/test_empty_keywords.py
tests/atest/external_import/__init__.py
tests/atest/external_import/test_external_import.py
tests/atest/external_library/__init__.py
tests/atest/external_library/test_external_library.py
tests/atest/import_with_variable/__init__.py
tests/atest/import_with_variable/test_import_with_variable.py
tests/atest/invalid_library/__init__.py
tests/atest/invalid_library/test_invalid_library.py
tests/atest/keyword_in_res_and_suite/__init__.py
tests/atest/keyword_in_res_and_suite/test_keyword_in_res_and_suite.py
tests/atest/library_from_resource/__init__.py
tests/atest/library_from_resource/test_library_from_resource.py
tests/atest/multiple_sources/__init__.py
tests/atest/multiple_sources/test_multiple_sources.py
tests/atest/nested_modules/__init__.py
tests/atest/nested_modules/test_nested_modules.py
tests/atest/pythonpath/__init__.py
tests/atest/pythonpath/test_python_path.py
tests/atest/recursive_import/__init__.py
tests/atest/recursive_import/test_recursive_import.py
robotframework_sherlock-0.3.0.dist-info/LICENSE
robotframework_sherlock-0.3.0.dist-info/METADATA
robotframework_sherlock-0.3.0.dist-info/WHEEL
robotframework_sherlock-0.3.0.dist-info/entry_points.txt
robotframework_sherlock-0.3.0.dist-info/top_level.txt
robotframework_sherlock-0.3.0.dist-info/RECORD
