Metadata-Version: 2.1
Name: robotframework-sherlock
Version: 0.3.0
Summary: Robot Framework code analysis tool
Home-page: https://github.com/bhirsz/robotframework-sherlock
Download-URL: https://pypi.org/project/robotframework-sherlock
Author: Bartlomiej Hirsz, Mateusz Nojek
Author-email: bartek.hirsz@gmail.com, matnojek@gmail.com
License: Apache License 2.0
Keywords: robotframework automation testautomation testing qa
Platform: any
Classifier: Development Status :: 2 - Pre-Alpha
Classifier: License :: OSI Approved :: Apache Software License
Classifier: Operating System :: OS Independent
Classifier: Programming Language :: Python
Classifier: Programming Language :: Python :: 3.7
Classifier: Programming Language :: Python :: 3.8
Classifier: Programming Language :: Python :: 3.9
Classifier: Framework :: Robot Framework
Classifier: Framework :: Robot Framework :: Tool
Classifier: Topic :: Software Development :: Testing
Classifier: Topic :: Software Development :: Quality Assurance
Classifier: Topic :: Utilities
Classifier: Intended Audience :: Developers
Requires-Python: >=3.8
License-File: LICENSE
Requires-Dist: robotframework >=4.1
Requires-Dist: toml >=0.10.2
Requires-Dist: pathspec ==0.9.*
Requires-Dist: jinja2
Requires-Dist: tabulate ==0.8.9
Requires-Dist: rich >=10.12.0
Provides-Extra: dev
Requires-Dist: coverage ; extra == 'dev'
Requires-Dist: pytest ; extra == 'dev'
Requires-Dist: robotframework-templateddata ; extra == 'dev'
